crmngr/__init__.py
crmngr/__main__.py
crmngr/cache.py
crmngr/cli.py
crmngr/config.py
crmngr/controlrepository.py
crmngr/cprint.py
crmngr/forgeapi.py
crmngr/git.py
crmngr/puppetfile.py
crmngr/utils.py
crmngr/version.py
crmngr-2.0.3.dist-info/DESCRIPTION.rst
crmngr-2.0.3.dist-info/METADATA
crmngr-2.0.3.dist-info/RECORD
crmngr-2.0.3.dist-info/WHEEL
crmngr-2.0.3.dist-info/entry_points.txt
crmngr-2.0.3.dist-info/metadata.json
crmngr-2.0.3.dist-info/top_level.txt
