Metadata-Version: 2.0
Name: crmngr
Version: 2.0.3
Summary: manage a r10k-style control repository
Home-page: https://github.com/vshn/crmngr
Author: Andre Keller
Author-email: andre.keller@vshn.ch
License: BSD
Platform: UNKNOWN
Classifier: Development Status :: 4 - Beta
Classifier: Environment :: Console
Classifier: Intended Audience :: System Administrators
Classifier: License :: OSI Approved :: BSD License
Classifier: Operating System :: Unix
Classifier: Programming Language :: Python :: 3 :: Only
Classifier: Topic :: System :: Systems Administration
Requires-Dist: natsort (>=4.0.0)
Requires-Dist: requests (>=2.1.0)
